blockchain_proofs/__init__.py
blockchain_proofs/chainpoint.py
blockchain_proofs-0.2.1.dist-info/DESCRIPTION.rst
blockchain_proofs-0.2.1.dist-info/METADATA
blockchain_proofs-0.2.1.dist-info/RECORD
blockchain_proofs-0.2.1.dist-info/WHEEL
blockchain_proofs-0.2.1.dist-info/metadata.json
blockchain_proofs-0.2.1.dist-info/top_level.txt
