Metadata-Version: 2.0
Name: blockchain-proofs
Version: 0.2.1
Summary: Implements chainpoint v2 proof of existence approach
Home-page: UNKNOWN
Author: Konstantinos Karasavvas
Author-email: kkarasavvas@gmail.com
License: MIT
Keywords: blockchain proof receipt chainpoint validation
Platform: UNKNOWN
Classifier: Development Status :: 4 - Beta
Classifier: Intended Audience :: Developers
Classifier: Programming Language :: Python :: 3
Requires-Dist: merkletools (>=1.0.2)
Requires-Dist: requests (>=2.13.0)
